{"runner": {"num_initial_experiments": null, "max_iterations": 20, "batch_size": 1, "f_tol": 1e-05, "max_restarts": 0}, "strategy": {"name": "MTBO", "transform": {"transform_domain": [{"type": "CategoricalVariable", "is_objective": false, "name": "catalyst", "description": "Catalyst type", "units": null, "levels": ["tBuXPhos", "tBuBrettPhos", "AlPhos"], "ds": {"index": ["tBuXPhos", "tBuBrettPhos", "AlPhos"], "columns": [["area_cat", "DATA"], ["M2_cat", "DATA"]], "data": [[460.7543, 67.2057], [518.8408, 89.8738], [819.933, 129.0808]]}}, {"type": "CategoricalVariable", "is_objective": false, "name": "base", "description": "Base", "units": null, "levels": ["DBU", "BTMG", "TMG", "TEA"], "ds": {"index": ["TEA", "TMG", "BTMG", "DBU"], "columns": [["area", "DATA"], ["M2", "DATA"]], "data": [[162.2992, 25.8165], [165.5447, 81.4847], [227.3523, 30.554], [192.4693, 59.8367]]}}, {"type": "ContinuousVariable", "is_objective": false, "name": "base_equivalents", "description": "Base equivalents", "units": null, "bounds": [1.0, 2.5]}, {"type": "ContinuousVariable", "is_objective": false, "name": "temperature", "description": "Temperature in degrees Celsius (\u00baC)", "units": null, "bounds": [30.0, 100.0]}, {"type": "ContinuousVariable", "is_objective": false, "name": "t_res", "description": "residence time in seconds (s)", "units": null, "bounds": [60.0, 1800.0]}, {"type": "ContinuousVariable", "is_objective": true, "name": "yield", "description": "Yield", "units": null, "bounds": [0.0, 1.0]}], "name": "Transform", "domain": [{"type": "CategoricalVariable", "is_objective": false, "name": "catalyst", "description": "Catalyst type", "units": null, "levels": ["tBuXPhos", "tBuBrettPhos", "AlPhos"], "ds": {"index": ["tBuXPhos", "tBuBrettPhos", "AlPhos"], "columns": [["area_cat", "DATA"], ["M2_cat", "DATA"]], "data": [[460.7543, 67.2057], [518.8408, 89.8738], [819.933, 129.0808]]}}, {"type": "CategoricalVariable", "is_objective": false, "name": "base", "description": "Base", "units": null, "levels": ["DBU", "BTMG", "TMG", "TEA"], "ds": {"index": ["TEA", "TMG", "BTMG", "DBU"], "columns": [["area", "DATA"], ["M2", "DATA"]], "data": [[162.2992, 25.8165], [165.5447, 81.4847], [227.3523, 30.554], [192.4693, 59.8367]]}}, {"type": "ContinuousVariable", "is_objective": false, "name": "base_equivalents", "description": "Base equivalents", "units": null, "bounds": [1.0, 2.5]}, {"type": "ContinuousVariable", "is_objective": false, "name": "temperature", "description": "Temperature in degrees Celsius (\u00baC)", "units": null, "bounds": [30.0, 100.0]}, {"type": "ContinuousVariable", "is_objective": false, "name": "t_res", "description": "residence time in seconds (s)", "units": null, "bounds": [60.0, 1800.0]}, {"type": "ContinuousVariable", "is_objective": true, "name": "yield", "description": "Yield", "units": null, "bounds": [0.0, 1.0]}], "transform_params": {}}, "strategy_params": {"all_experiments": {"index": [0, 1, 0, 0, 0, 0, 0, 0, 0, 0, 0, 0, 0, 0, 0, 0, 0, 0, 0, 0], "columns": [["catalyst", "DATA"], ["base", "DATA"], ["base_equivalents", "DATA"], ["temperature", "DATA"], ["t_res", "DATA"], ["yield", "DATA"], ["computation_t", "METADATA"], ["experiment_t", "METADATA"], ["strategy", "METADATA"], ["task", "METADATA"]], "data": [["tBuBrettPhos", "TEA", 1.375, 47.5, 1365.0, 0.031087905168533325, 0.0, 0.0387418270111084, "LHS", 1.0], ["tBuXPhos", "TEA", 2.125, 82.5, 495.0, 0.08582445979118347, 0.0, 0.03720808029174805, "LHS", 1.0], ["tBuBrettPhos", "TMG", 1.4991494417190552, 36.167755126953125, 1212.3399658203125, 0.14286355674266815, 1.2686350345611572, 0.030543088912963867, "MTBO", 1.0], ["tBuXPhos", "TEA", 1.5148553848266602, 33.97200393676758, 1495.070068359375, 0.0962250828742981, 1.5614850521087646, 0.03043198585510254, "MTBO", 1.0], ["tBuBrettPhos", "TMG", 1.0325247049331665, 32.181617736816406, 228.042236328125, 0.05271881818771362, 1.4036962985992432, 0.0269620418548584, "MTBO", 1.0], ["AlPhos", "TEA", 2.1435296535491943, 80.57182312011719, 73.68328857421875, 0.11817464977502823, 1.2483539581298828, 0.028758764266967773, "MTBO", 1.0], ["tBuXPhos", "TEA", 1.0969215631484985, 36.80966567993164, 92.426025390625, 0.010050802491605282, 1.4072411060333252, 0.028034210205078125, "MTBO", 1.0], ["AlPhos", "TEA", 1.4467252492904663, 46.473052978515625, 605.38525390625, 0.19592273235321045, 1.390338659286499, 0.0296630859375, "MTBO", 1.0], ["AlPhos", "TEA", 2.256354331970215, 30.828495025634766, 546.509765625, 0.12315217405557632, 2.118194103240967, 0.028336763381958008, "MTBO", 1.0], ["tBuBrettPhos", "TEA", 1.0673608779907227, 96.89002990722656, 170.10772705078125, 0.2484760582447052, 1.445608139038086, 0.02947402000427246, "MTBO", 1.0], ["tBuBrettPhos", "BTMG", 1.5417946577072144, 98.40274810791016, 995.490966796875, 0.9726774096488953, 2.680356740951538, 0.027546167373657227, "MTBO", 1.0], ["tBuBrettPhos", "BTMG", 1.5471522808074951, 99.63654327392578, 885.6548461914062, 0.9872915148735046, 4.138642072677612, 0.0281069278717041, "MTBO", 1.0], ["tBuBrettPhos", "BTMG", 1.491419792175293, 98.85358428955078, 1178.6201171875, 0.9510895013809204, 1.847771167755127, 0.029827117919921875, "MTBO", 1.0], ["tBuBrettPhos", "BTMG", 1.3932420015335083, 94.94700622558594, 1012.8585205078125, 0.961902916431427, 2.80304217338562, 0.03448319435119629, "MTBO", 1.0], ["tBuBrettPhos", "BTMG", 1.5445362329483032, 100.0, 1099.391845703125, 0.9626741409301758, 3.324009895324707, 0.0282289981842041, "MTBO", 1.0], ["tBuBrettPhos", "BTMG", 1.4963829517364502, 96.83975982666016, 896.980224609375, 0.9809967279434204, 3.114919900894165, 0.028236865997314453, "MTBO", 1.0], ["tBuBrettPhos", "BTMG", 1.7191025018692017, 100.0, 841.56640625, 0.9865299463272095, 2.1047701835632324, 0.028795957565307617, "MTBO", 1.0], ["tBuBrettPhos", "BTMG", 1.6924875974655151, 97.6346206665039, 965.921630859375, 0.9699214100837708, 2.629979133605957, 0.02884387969970703, "MTBO", 1.0], ["tBuBrettPhos", "BTMG", 1.7132596969604492, 99.98907470703125, 840.1961669921875, 0.9870069622993469, 2.8057498931884766, 0.028477191925048828, "MTBO", 1.0], ["tBuBrettPhos", "BTMG", 1.4922822713851929, 99.99871826171875, 986.833740234375, 0.9763621091842651, 2.380018949508667, 0.028078079223632812, "MTBO", 1.0]]}, "categorical_method": "one-hot", "task": 1}}, "experiment": {"domain": [{"type": "CategoricalVariable", "is_objective": false, "name": "catalyst", "description": "Catalyst type", "units": null, "levels": ["tBuXPhos", "tBuBrettPhos", "AlPhos"], "ds": {"index": ["tBuXPhos", "tBuBrettPhos", "AlPhos"], "columns": [["area_cat", "DATA"], ["M2_cat", "DATA"]], "data": [[460.7543, 67.2057], [518.8408, 89.8738], [819.933, 129.0808]]}}, {"type": "CategoricalVariable", "is_objective": false, "name": "base", "description": "Base", "units": null, "levels": ["DBU", "BTMG", "TMG", "TEA"], "ds": {"index": ["TEA", "TMG", "BTMG", "DBU"], "columns": [["area", "DATA"], ["M2", "DATA"]], "data": [[162.2992, 25.8165], [165.5447, 81.4847], [227.3523, 30.554], [192.4693, 59.8367]]}}, {"type": "ContinuousVariable", "is_objective": false, "name": "base_equivalents", "description": "Base equivalents", "units": null, "bounds": [1.0, 2.5]}, {"type": "ContinuousVariable", "is_objective": false, "name": "temperature", "description": "Temperature in degrees Celsius (\u00baC)", "units": null, "bounds": [30.0, 100.0]}, {"type": "ContinuousVariable", "is_objective": false, "name": "t_res", "description": "residence time in seconds (s)", "units": null, "bounds": [60.0, 1800.0]}, {"type": "ContinuousVariable", "is_objective": true, "name": "yield", "description": "Yield", "units": null, "bounds": [0.0, 1.0]}], "name": "ExperimentalEmulator", "data": {"index": [0, 1, 2, 3, 4, 5, 6, 7, 8, 9, 10, 11, 12, 13, 14, 15, 16, 17, 18, 19, 20], "columns": [["catalyst", "DATA"], ["base", "DATA"], ["base_equivalents", "DATA"], ["temperature", "DATA"], ["t_res", "DATA"], ["yield", "DATA"], ["computation_t", "METADATA"], ["experiment_t", "METADATA"], ["strategy", "METADATA"], ["task", "METADATA"]], "data": [["tBuBrettPhos", "TEA", 1.375, 47.5, 1365.0, 0.031087905168533325, 0.0, 0.0387418270111084, "LHS", 1.0], ["tBuXPhos", "TEA", 2.125, 82.5, 495.0, 0.08582445979118347, 0.0, 0.03720808029174805, "LHS", 1.0], ["tBuBrettPhos", "TMG", 1.4991494417190552, 36.167755126953125, 1212.3399658203125, 0.14286355674266815, 1.2686350345611572, 0.030543088912963867, "MTBO", 1.0], ["tBuXPhos", "TEA", 1.5148553848266602, 33.97200393676758, 1495.070068359375, 0.0962250828742981, 1.5614850521087646, 0.03043198585510254, "MTBO", 1.0], ["tBuBrettPhos", "TMG", 1.0325247049331665, 32.181617736816406, 228.042236328125, 0.05271881818771362, 1.4036962985992432, 0.0269620418548584, "MTBO", 1.0], ["AlPhos", "TEA", 2.1435296535491943, 80.57182312011719, 73.68328857421875, 0.11817464977502823, 1.2483539581298828, 0.028758764266967773, "MTBO", 1.0], ["tBuXPhos", "TEA", 1.0969215631484985, 36.80966567993164, 92.426025390625, 0.010050802491605282, 1.4072411060333252, 0.028034210205078125, "MTBO", 1.0], ["AlPhos", "TEA", 1.4467252492904663, 46.473052978515625, 605.38525390625, 0.19592273235321045, 1.390338659286499, 0.0296630859375, "MTBO", 1.0], ["AlPhos", "TEA", 2.256354331970215, 30.828495025634766, 546.509765625, 0.12315217405557632, 2.118194103240967, 0.028336763381958008, "MTBO", 1.0], ["tBuBrettPhos", "TEA", 1.0673608779907227, 96.89002990722656, 170.10772705078125, 0.2484760582447052, 1.445608139038086, 0.02947402000427246, "MTBO", 1.0], ["tBuBrettPhos", "BTMG", 1.5417946577072144, 98.40274810791016, 995.490966796875, 0.9726774096488953, 2.680356740951538, 0.027546167373657227, "MTBO", 1.0], ["tBuBrettPhos", "BTMG", 1.5471522808074951, 99.63654327392578, 885.6548461914062, 0.9872915148735046, 4.138642072677612, 0.0281069278717041, "MTBO", 1.0], ["tBuBrettPhos", "BTMG", 1.491419792175293, 98.85358428955078, 1178.6201171875, 0.9510895013809204, 1.847771167755127, 0.029827117919921875, "MTBO", 1.0], ["tBuBrettPhos", "BTMG", 1.3932420015335083, 94.94700622558594, 1012.8585205078125, 0.961902916431427, 2.80304217338562, 0.03448319435119629, "MTBO", 1.0], ["tBuBrettPhos", "BTMG", 1.5445362329483032, 100.0, 1099.391845703125, 0.9626741409301758, 3.324009895324707, 0.0282289981842041, "MTBO", 1.0], ["tBuBrettPhos", "BTMG", 1.4963829517364502, 96.83975982666016, 896.980224609375, 0.9809967279434204, 3.114919900894165, 0.028236865997314453, "MTBO", 1.0], ["tBuBrettPhos", "BTMG", 1.7191025018692017, 100.0, 841.56640625, 0.9865299463272095, 2.1047701835632324, 0.028795957565307617, "MTBO", 1.0], ["tBuBrettPhos", "BTMG", 1.6924875974655151, 97.6346206665039, 965.921630859375, 0.9699214100837708, 2.629979133605957, 0.02884387969970703, "MTBO", 1.0], ["tBuBrettPhos", "BTMG", 1.7132596969604492, 99.98907470703125, 840.1961669921875, 0.9870069622993469, 2.8057498931884766, 0.028477191925048828, "MTBO", 1.0], ["tBuBrettPhos", "BTMG", 1.4922822713851929, 99.99871826171875, 986.833740234375, 0.9763621091842651, 2.380018949508667, 0.028078079223632812, "MTBO", 1.0], ["tBuBrettPhos", "BTMG", 1.374122142791748, 99.86296844482422, 1006.055908203125, 0.9725362062454224, 2.5817477703094482, 0.027399778366088867, "MTBO", 1.0]]}, "experiment_params": {"model_name": "baumgartner_aniline_cn_crosscoupling", "regressor_name": "ANNRegressor", "n_features": 10, "n_examples": 96, "descriptors_features": [], "output_variable_names": ["yield"], "predictors": [{"input_preprocessor": {"num": {"mean_": [1.6559957171333333, 69.63333333333334, 675.2387380961666], "var_": [0.24093575016750415, 906.7308888888889, 253625.04696145264], "scale_": [0.4908520654611776, 30.11197251740392, 503.6120004144586], "n_samples_seen_": 60}}, "output_preprocessor": {"mean_": [0.5805532822851092], "var_": [0.1785550681951766], "scale_": [0.42255776906261777], "n_samples_seen_": 60}}, {"input_preprocessor": {"num": {"mean_": [1.683371605967213, 74.62295081967213, 715.8182047760656], "var_": [0.24120375329778332, 866.5532437516797, 223573.2988868711], "scale_": [0.49112498745002103, 29.43727643230059, 472.83538243967223], "n_samples_seen_": 61}}, "output_preprocessor": {"mean_": [0.6254036210660563], "var_": [0.16832977557768586], "scale_": [0.4102801184284779], "n_samples_seen_": 61}}, {"input_preprocessor": {"num": {"mean_": [1.6615540930327868, 69.30163934426228, 681.7872910763934], "var_": [0.24927125858022928, 924.5657350174685, 269346.5438305566], "scale_": [0.49927072674074263, 30.40667254103067, 518.9860728676219], "n_samples_seen_": 61}}, "output_preprocessor": {"mean_": [0.5703947171110844], "var_": [0.18538124205880477], "scale_": [0.43055922015305254], "n_samples_seen_": 61}}, {"input_preprocessor": {"num": {"mean_": [1.628605248, 72.78196721311477, 735.1206038822951], "var_": [0.24907596673949953, 907.5027895726955, 244282.01121683227], "scale_": [0.4990751113204299, 30.124786963108892, 494.24893648528194], "n_samples_seen_": 61}}, "output_preprocessor": {"mean_": [0.6131021287750269], "var_": [0.17856050759065348], "scale_": [0.4225642052879698], "n_samples_seen_": 61}}, {"input_preprocessor": {"num": {"mean_": [1.6073154240819671, 73.0311475409836, 743.0736161352461], "var_": [0.2525966705755136, 848.4237839290512, 251362.03663802444], "scale_": [0.5025899626688873, 29.12771504819853, 501.3601865306263], "n_samples_seen_": 61}}, "output_preprocessor": {"mean_": [0.564398883872467], "var_": [0.18049929808199283], "scale_": [0.4248520896523787], "n_samples_seen_": 61}}]}, "extras": [{}, {}, {}, {}, {}, {}, {}, {}, {}, {}, {}, {}, {}, {}, {}, {}, {}, {}, {}, {}, {}, {}, {}, {}, {}, {}, {}, {}, {}, {}, {}, {}, {}, {}, {}, {}, {}, {}, {}, {}, {}, {}]}}